lammps_parse/__init__.py
lammps_parse/_version.py
lammps_parse/readers.py
lammps_parse/utils.py
lammps_parse/writers.py
lammps_parse-0.1.0.dist-info/LICENSE
lammps_parse-0.1.0.dist-info/METADATA
lammps_parse-0.1.0.dist-info/WHEEL
lammps_parse-0.1.0.dist-info/top_level.txt
lammps_parse-0.1.0.dist-info/RECORD
