Metadata-Version: 2.1
Name: lammps-parse
Version: 0.1.0
Summary: Input file writers and output file parsers for Lammps.
Home-page: UNKNOWN
Author: Adam J. Plowman, Maria S. Yankova
Author-email: adam.plowman@manchester.ac.uk
License: UNKNOWN
Project-URL: Github, https://github.com/aplowman/lammps-parse
Platform: UNKNOWN
Classifier: Development Status :: 4 - Beta
Classifier: Intended Audience :: Science/Research
Classifier: Topic :: Scientific/Engineering
Classifier: Programming Language :: Python :: 3.5
Classifier: Programming Language :: Python :: 3.6
Classifier: Programming Language :: Python :: 3.7
Classifier: License :: OSI Approved :: Mozilla Public License 2.0 (MPL 2.0)
Classifier: Operating System :: OS Independent
Requires-Dist: numpy
